versionwarning/__init__.py
versionwarning/extension.py
versionwarning/signals.py
versionwarning/_static/js/versionwarning.js
modern_sphinx_version_warning-1.1.6.dist-info/LICENSE
modern_sphinx_version_warning-1.1.6.dist-info/METADATA
modern_sphinx_version_warning-1.1.6.dist-info/WHEEL
modern_sphinx_version_warning-1.1.6.dist-info/top_level.txt
modern_sphinx_version_warning-1.1.6.dist-info/RECORD
