Metadata-Version: 2.1
Name: modern-sphinx-version-warning
Version: 1.1.6
Summary: Sphinx extension to add a warning banner
Home-page: https://github.com/grahamsh-llk/sphinx-version-warning
Author: Graham Howard
Author-email: graham@grahamsh.com
Classifier: Programming Language :: Python :: 3
Classifier: License :: OSI Approved :: MIT License
Classifier: Operating System :: OS Independent
License-File: LICENSE
Requires-Dist: sphinx
